asmrmanager-2.9.0.dist-info/METADATA
asmrmanager-2.9.0.dist-info/WHEEL
asmrmanager-2.9.0.dist-info/entry_points.txt
asmrmanager-2.9.0.dist-info/licenses/LICENSE
asmrmanager/__init__.py
asmrmanager/__main__.py
asmrmanager/_version.py
asmrmanager/cli/core.py
asmrmanager/cli/dl.py
asmrmanager/cli/file.py
asmrmanager/cli/hold.py
asmrmanager/cli/info.py
asmrmanager/cli/main.py
asmrmanager/cli/pl.py
asmrmanager/cli/play.py
asmrmanager/cli/query.py
asmrmanager/cli/review.py
asmrmanager/cli/sql.py
asmrmanager/cli/utils.py
asmrmanager/cli/view.py
asmrmanager/cli/vote.py
asmrmanager/cli/which.py
asmrmanager/common/__init__.py
asmrmanager/common/browse_params.py
asmrmanager/common/download_params.py
asmrmanager/common/fileconverter.py
asmrmanager/common/output.py
asmrmanager/common/parse_filter.py
asmrmanager/common/rj_parse.py
asmrmanager/common/select.py
asmrmanager/common/subtitle.py
asmrmanager/common/types.py
asmrmanager/common/vtt2lrc.py
asmrmanager/config.py
asmrmanager/database/__init__.py
asmrmanager/database/__pycache__/database.d.er
asmrmanager/database/__pycache__/engine.d.er
asmrmanager/database/__pycache__/q_func.d.er
asmrmanager/database/database.py
asmrmanager/database/engine.py
asmrmanager/database/manage.py
asmrmanager/database/orm_type.py
asmrmanager/database/q_func.py
asmrmanager/database/utils/__init__.py
asmrmanager/database/utils/add2db.py
asmrmanager/database/utils/uuid_sqlite.py
asmrmanager/filemanager/__init__.py
asmrmanager/filemanager/appdirs_.py
asmrmanager/filemanager/exceptions.py
asmrmanager/filemanager/file_zipper.py
asmrmanager/filemanager/manager.py
asmrmanager/filemanager/resources/akarin.jpg
asmrmanager/filemanager/resources/config.example.toml
asmrmanager/filemanager/resources/sqls.example/circle_name.sql
asmrmanager/filemanager/resources/sqls.example/score.sql
asmrmanager/filemanager/resources/sqls.example/search.sql
asmrmanager/filemanager/resources/sqls.example/tags.sql
asmrmanager/filemanager/resources/sqls.example/test.sql
asmrmanager/filemanager/resources/sqls.example/vas.sql
asmrmanager/filemanager/utils.py
asmrmanager/logger/__init__.py
asmrmanager/lrcplayer/__init__.py
asmrmanager-2.9.0.dist-info/RECORD
