Metadata-Version: 2.1
Name: ASMRManager
Version: 2.9.0
Summary: download, manage and play the voices on asmr.one
Keywords: asmr,downloader,music,player,manager,cli,tui,commandline,terminal
Author-Email: SLQY <sqiyel@gmail.com>
License: MIT
Project-URL: repository, https://github.com/slqy123/ASMRManager
Requires-Python: >=3.12
Requires-Dist: aiohttp>=3.8.6
Requires-Dist: chardet>=5.1.0
Requires-Dist: click>=8.1.3
Requires-Dist: pylrc==0.1.2
Requires-Dist: rich>=13.0.0
Requires-Dist: SQLAlchemy>=2.0.36
Requires-Dist: textual>=1
Requires-Dist: mutagen>=1.46.0
Requires-Dist: appdirs>=1.4.4
Requires-Dist: toml>=0.10.2
Requires-Dist: beaupy>=3.11.0
Requires-Dist: asyncstdlib>=3.13.1
Requires-Dist: xxhash>=3.5.0
Provides-Extra: pygame
Requires-Dist: pygame>=2.5.0; extra == "pygame"
Provides-Extra: mpd
Requires-Dist: python-mpd2>=3.1.0; extra == "mpd"
Provides-Extra: aria2
Requires-Dist: aioaria2>=1.3.4; extra == "aria2"
Provides-Extra: idm
Requires-Dist: comtypes>=1.2.0; extra == "idm"
Provides-Extra: tui
Requires-Dist: trogon>=0.4.0; extra == "tui"
Provides-Extra: player
Requires-Dist: sounddevice>=0.5.3; extra == "player"
Requires-Dist: soundfile>=0.13.1; extra == "player"
Provides-Extra: subtitle
Requires-Dist: faster-whisper>=1.1.1; extra == "subtitle"
Requires-Dist: ctranslate2>=4.6.0; extra == "subtitle"
Provides-Extra: image
Requires-Dist: textual-image>=0.8.5; extra == "image"
Provides-Extra: dev
Requires-Dist: pyinstrument>=4.6.2; extra == "dev"
Requires-Dist: viztracer>=0.16.3; extra == "dev"
Requires-Dist: ruff>=0.11.5; extra == "dev"
Requires-Dist: mypy>=1.15.0; extra == "dev"
Provides-Extra: all
Requires-Dist: asmrmanager[aria2,idm,image,player,subtitle,tui]; extra == "all"
